{
  "en": {
    "nameSuffix": "You",
    "endButton": "Finish session",
    "controls": {
      "start": "Start",
      "next": "Next",
      "prev": "Back"
    },
    "notifications": {
      "joined": "{{name}} joined",
      "left": "{{name}} left",
      "networkQuality": "Unrealiable network connection",
      "muted": "You are muted"
    },
    "permissionsAlert": {
      "camera": {
        "title": "Permission for camera was denied",
        "message": "Allow 29k sessions to access your camera so that you can participate in the session. This will restart the 29k session app. ",
        "dismiss": "Cancel",
        "confirm": "Open Settings"
      },
      "microphone": {
        "title": "Permission for microphone was denied",
        "message": "Allow 29k sessions to access your microphone so that you can participate in the session. This will restart the 29k session app. ",
        "dismiss": "Cancel",
        "confirm": "Open Settings"
      }
    }
  },
  "pt": {
    "nameSuffix": "Tu",
    "endButton": "Terminar sessão",
    "controls": {
      "start": "Iniciar",
      "next": "Próximo",
      "prev": "Voltar"
    },
    "notifications": {
      "joined": "{{name}} juntou-se",
      "left": "{{name}} saiu",
      "networkQuality": "Ligação de rede instável",
      "muted": "Estás sem som"
    }
  },
  "sv": {
    "nameSuffix": "Du",
    "endButton": "Avsluta",
    "controls": {
      "start": "Starta",
      "next": "Nästa",
      "prev": "Tillbaka"
    },
    "notifications": {
      "joined": "{{name}} gick med",
      "left": "{{name}} lämnade",
      "networkQuality": "Ostabilt nätverk",
      "muted": "Din mikrofon är av"
    }
  },
  "es": {}
}
